[{"YEAR": "2014", "values": [{"value": 0.42, "LIWC": "I"}, {"value": 0.01, "LIWC": "We"}, {"value": 0.0, "LIWC": "They"}, {"value": 0.73, "LIWC": "Social"}, {"value": 0.02, "LIWC": "Family"}, {"value": 0.0, "LIWC": "Friends"}, {"value": 0.3, "LIWC": "Affect"}]}, {"YEAR": "2015", "values": [{"value": 0.27, "LIWC": "I"}, {"value": 0.09, "LIWC": "We"}, {"value": 0.02, "LIWC": "They"}, {"value": 0.67, "LIWC": "Social"}, {"value": 0.0, "LIWC": "Family"}, {"value": 0.0, "LIWC": "Friends"}, {"value": 0.38, "LIWC": "Affect"}]}, {"YEAR": "2016", "values": [{"value": 0.26, "LIWC": "I"}, {"value": 0.12, "LIWC": "We"}, {"value": 0.03, "LIWC": "They"}, {"value": 1.23, "LIWC": "Social"}, {"value": 0.0, "LIWC": "Family"}, {"value": 0.0, "LIWC": "Friends"}, {"value": 0.49, "LIWC": "Affect"}]}, {"YEAR": "2017", "values": [{"value": 0.04, "LIWC": "I"}, {"value": 0.0, "LIWC": "We"}, {"value": 0.01, "LIWC": "They"}, {"value": 0.12, "LIWC": "Social"}, {"value": 0.0, "LIWC": "Family"}, {"value": 0.0, "LIWC": "Friends"}, {"value": 0.03, "LIWC": "Affect"}]}]