[{"YEAR": "2014", "values": [{"value": 0.0386363636, "LIWC": "I"}, {"value": 0.0, "LIWC": "We"}, {"value": 0.0031818182, "LIWC": "They"}, {"value": 0.0540909091, "LIWC": "Social"}, {"value": 0.0031818182, "LIWC": "Family"}, {"value": 0.0004545455, "LIWC": "Friends"}, {"value": 0.0418181818, "LIWC": "Affect"}]}, {"YEAR": "2015", "values": [{"value": 0.0296666667, "LIWC": "I"}, {"value": 0.002, "LIWC": "We"}, {"value": 0.0043333333, "LIWC": "They"}, {"value": 0.0623333333, "LIWC": "Social"}, {"value": 0.0, "LIWC": "Family"}, {"value": 0.001, "LIWC": "Friends"}, {"value": 0.0503333333, "LIWC": "Affect"}]}, {"YEAR": "2016", "values": [{"value": 0.0208333333, "LIWC": "I"}, {"value": 0.0, "LIWC": "We"}, {"value": 0.0016666667, "LIWC": "They"}, {"value": 0.0516666667, "LIWC": "Social"}, {"value": 0.0, "LIWC": "Family"}, {"value": 0.0, "LIWC": "Friends"}, {"value": 0.0383333333, "LIWC": "Affect"}]}, {"YEAR": "2017", "values": [{"value": 0.04, "LIWC": "I"}, {"value": 0.0, "LIWC": "We"}, {"value": 0.0, "LIWC": "They"}, {"value": 0.04, "LIWC": "Social"}, {"value": 0.0, "LIWC": "Family"}, {"value": 0.0, "LIWC": "Friends"}, {"value": 0.04, "LIWC": "Affect"}]}]