[{"YEAR": "2014", "values": [{"value": 0.0164285714, "LIWC": "I"}, {"value": 0.0076190476, "LIWC": "We"}, {"value": 0.0125, "LIWC": "They"}, {"value": 0.0936904762, "LIWC": "Social"}, {"value": 0.000952381, "LIWC": "Family"}, {"value": 0.0002380952, "LIWC": "Friends"}, {"value": 0.053452381, "LIWC": "Affect"}]}, {"YEAR": "2015", "values": [{"value": 0.0119776715, "LIWC": "I"}, {"value": 0.0050079745, "LIWC": "We"}, {"value": 0.0128389155, "LIWC": "They"}, {"value": 0.092169059, "LIWC": "Social"}, {"value": 0.0010207337, "LIWC": "Family"}, {"value": 0.0003030303, "LIWC": "Friends"}, {"value": 0.0492025518, "LIWC": "Affect"}]}, {"YEAR": "2016", "values": [{"value": 0.0144628099, "LIWC": "I"}, {"value": 0.006231405, "LIWC": "We"}, {"value": 0.0123801653, "LIWC": "They"}, {"value": 0.0963305785, "LIWC": "Social"}, {"value": 0.001338843, "LIWC": "Family"}, {"value": 0.0005785124, "LIWC": "Friends"}, {"value": 0.0590909091, "LIWC": "Affect"}]}, {"YEAR": "2017", "values": [{"value": 0.0184210526, "LIWC": "I"}, {"value": 0.0034210526, "LIWC": "We"}, {"value": 0.0121052632, "LIWC": "They"}, {"value": 0.1, "LIWC": "Social"}, {"value": 0.0013157895, "LIWC": "Family"}, {"value": 0.0007894737, "LIWC": "Friends"}, {"value": 0.0528947368, "LIWC": "Affect"}]}]