[{"YEAR": "2014", "values": [{"value": 0.024, "LIWC": "I"}, {"value": 0.006, "LIWC": "We"}, {"value": 0.004, "LIWC": "They"}, {"value": 0.09, "LIWC": "Social"}, {"value": 0.0, "LIWC": "Family"}, {"value": 0.002, "LIWC": "Friends"}, {"value": 0.054, "LIWC": "Affect"}]}, {"YEAR": "2015", "values": [{"value": 0.0133333333, "LIWC": "I"}, {"value": 0.0033333333, "LIWC": "We"}, {"value": 0.0033333333, "LIWC": "They"}, {"value": 0.065, "LIWC": "Social"}, {"value": 0.0, "LIWC": "Family"}, {"value": 0.0, "LIWC": "Friends"}, {"value": 0.0283333333, "LIWC": "Affect"}]}, {"YEAR": "2016", "values": [{"value": 0.0066666667, "LIWC": "I"}, {"value": 0.0033333333, "LIWC": "We"}, {"value": 0.0066666667, "LIWC": "They"}, {"value": 0.0933333333, "LIWC": "Social"}, {"value": 0.0, "LIWC": "Family"}, {"value": 0.01, "LIWC": "Friends"}, {"value": 0.0466666667, "LIWC": "Affect"}]}]