[{"YEAR": "2015", "values": [{"value": 0.0176086957, "LIWC": "I"}, {"value": 0.0047826087, "LIWC": "We"}, {"value": 0.0065217391, "LIWC": "They"}, {"value": 0.0693478261, "LIWC": "Social"}, {"value": 0.0006521739, "LIWC": "Family"}, {"value": 0.0, "LIWC": "Friends"}, {"value": 0.0354347826, "LIWC": "Affect"}]}, {"YEAR": "2016", "values": [{"value": 0.0179661017, "LIWC": "I"}, {"value": 0.0001694915, "LIWC": "We"}, {"value": 0.0062711864, "LIWC": "They"}, {"value": 0.0662711864, "LIWC": "Social"}, {"value": 0.0, "LIWC": "Family"}, {"value": 0.0, "LIWC": "Friends"}, {"value": 0.0283050847, "LIWC": "Affect"}]}]