[{"YEAR": "2014", "values": [{"value": 12.28, "LIWC": "I"}, {"value": 0.4, "LIWC": "We"}, {"value": 0.59, "LIWC": "They"}, {"value": 12.68, "LIWC": "Social"}, {"value": 0.09, "LIWC": "Family"}, {"value": 0.08, "LIWC": "Friends"}, {"value": 10.33, "LIWC": "Affect"}]}, {"YEAR": "2015", "values": [{"value": 15.27, "LIWC": "I"}, {"value": 0.4, "LIWC": "We"}, {"value": 0.54, "LIWC": "They"}, {"value": 16.04, "LIWC": "Social"}, {"value": 0.1, "LIWC": "Family"}, {"value": 0.18, "LIWC": "Friends"}, {"value": 13.82, "LIWC": "Affect"}]}, {"YEAR": "2016", "values": [{"value": 16.02, "LIWC": "I"}, {"value": 0.21, "LIWC": "We"}, {"value": 0.54, "LIWC": "They"}, {"value": 14.96, "LIWC": "Social"}, {"value": 0.06, "LIWC": "Family"}, {"value": 0.18, "LIWC": "Friends"}, {"value": 13.17, "LIWC": "Affect"}]}, {"YEAR": "2017", "values": [{"value": 4.15, "LIWC": "I"}, {"value": 0.14, "LIWC": "We"}, {"value": 0.27, "LIWC": "They"}, {"value": 5.24, "LIWC": "Social"}, {"value": 0.02, "LIWC": "Family"}, {"value": 0.05, "LIWC": "Friends"}, {"value": 4.07, "LIWC": "Affect"}]}]