[{"YEAR": "2014", "values": [{"value": 0.0138888889, "LIWC": "I"}, {"value": 0.005, "LIWC": "We"}, {"value": 0.0044444444, "LIWC": "They"}, {"value": 0.0733333333, "LIWC": "Social"}, {"value": 0.0, "LIWC": "Family"}, {"value": 0.0022222222, "LIWC": "Friends"}, {"value": 0.0138888889, "LIWC": "Affect"}]}, {"YEAR": "2015", "values": [{"value": 0.0215384615, "LIWC": "I"}, {"value": 0.0030769231, "LIWC": "We"}, {"value": 0.0015384615, "LIWC": "They"}, {"value": 0.0630769231, "LIWC": "Social"}, {"value": 0.0023076923, "LIWC": "Family"}, {"value": 0.0, "LIWC": "Friends"}, {"value": 0.0276923077, "LIWC": "Affect"}]}, {"YEAR": "2016", "values": [{"value": 0.02, "LIWC": "I"}, {"value": 0.0, "LIWC": "We"}, {"value": 0.0, "LIWC": "They"}, {"value": 0.07, "LIWC": "Social"}, {"value": 0.0, "LIWC": "Family"}, {"value": 0.0, "LIWC": "Friends"}, {"value": 0.05, "LIWC": "Affect"}]}]