[{"YEAR": "2015", "values": [{"value": 0.0125, "LIWC": "I"}, {"value": 0.0025, "LIWC": "We"}, {"value": 0.00625, "LIWC": "They"}, {"value": 0.09625, "LIWC": "Social"}, {"value": 0.0, "LIWC": "Family"}, {"value": 0.0, "LIWC": "Friends"}, {"value": 0.0375, "LIWC": "Affect"}]}, {"YEAR": "2016", "values": [{"value": 0.015625, "LIWC": "I"}, {"value": 0.00375, "LIWC": "We"}, {"value": 0.00625, "LIWC": "They"}, {"value": 0.058125, "LIWC": "Social"}, {"value": 0.0, "LIWC": "Family"}, {"value": 0.0, "LIWC": "Friends"}, {"value": 0.039375, "LIWC": "Affect"}]}, {"YEAR": "2017", "values": [{"value": 0.0188888889, "LIWC": "I"}, {"value": 0.0022222222, "LIWC": "We"}, {"value": 0.0055555556, "LIWC": "They"}, {"value": 0.0722222222, "LIWC": "Social"}, {"value": 0.0, "LIWC": "Family"}, {"value": 0.0, "LIWC": "Friends"}, {"value": 0.04, "LIWC": "Affect"}]}]