[{"YEAR": "2014", "values": [{"value": 0.0646666667, "LIWC": "I"}, {"value": 0.006, "LIWC": "We"}, {"value": 0.0026666667, "LIWC": "They"}, {"value": 0.07, "LIWC": "Social"}, {"value": 0.0006666667, "LIWC": "Family"}, {"value": 0.004, "LIWC": "Friends"}, {"value": 0.0473333333, "LIWC": "Affect"}]}, {"YEAR": "2015", "values": [{"value": 0.0447368421, "LIWC": "I"}, {"value": 0.0026315789, "LIWC": "We"}, {"value": 0.0026315789, "LIWC": "They"}, {"value": 0.0863157895, "LIWC": "Social"}, {"value": 0.0005263158, "LIWC": "Family"}, {"value": 0.0026315789, "LIWC": "Friends"}, {"value": 0.0547368421, "LIWC": "Affect"}]}, {"YEAR": "2016", "values": [{"value": 0.045, "LIWC": "I"}, {"value": 0.003125, "LIWC": "We"}, {"value": 0.00875, "LIWC": "They"}, {"value": 0.081875, "LIWC": "Social"}, {"value": 0.00125, "LIWC": "Family"}, {"value": 0.001875, "LIWC": "Friends"}, {"value": 0.060625, "LIWC": "Affect"}]}, {"YEAR": "2017", "values": [{"value": 0.044, "LIWC": "I"}, {"value": 0.006, "LIWC": "We"}, {"value": 0.004, "LIWC": "They"}, {"value": 0.086, "LIWC": "Social"}, {"value": 0.0, "LIWC": "Family"}, {"value": 0.002, "LIWC": "Friends"}, {"value": 0.064, "LIWC": "Affect"}]}]