[{"YEAR": "2014", "values": [{"value": 0.075, "LIWC": "I"}, {"value": 0.01, "LIWC": "We"}, {"value": 0.0025, "LIWC": "They"}, {"value": 0.1125, "LIWC": "Social"}, {"value": 0.005, "LIWC": "Family"}, {"value": 0.0025, "LIWC": "Friends"}, {"value": 0.05875, "LIWC": "Affect"}]}, {"YEAR": "2015", "values": [{"value": 0.050625, "LIWC": "I"}, {"value": 0.004375, "LIWC": "We"}, {"value": 0.005625, "LIWC": "They"}, {"value": 0.085625, "LIWC": "Social"}, {"value": 0.003125, "LIWC": "Family"}, {"value": 0.00125, "LIWC": "Friends"}, {"value": 0.05875, "LIWC": "Affect"}]}, {"YEAR": "2016", "values": [{"value": 0.0347368421, "LIWC": "I"}, {"value": 0.0084210526, "LIWC": "We"}, {"value": 0.0042105263, "LIWC": "They"}, {"value": 0.0810526316, "LIWC": "Social"}, {"value": 0.0010526316, "LIWC": "Family"}, {"value": 0.0021052632, "LIWC": "Friends"}, {"value": 0.0357894737, "LIWC": "Affect"}]}, {"YEAR": "2017", "values": [{"value": 0.05, "LIWC": "I"}, {"value": 0.0, "LIWC": "We"}, {"value": 0.0033333333, "LIWC": "They"}, {"value": 0.0933333333, "LIWC": "Social"}, {"value": 0.0033333333, "LIWC": "Family"}, {"value": 0.0, "LIWC": "Friends"}, {"value": 0.0533333333, "LIWC": "Affect"}]}]