[{"YEAR": "2014", "values": [{"value": 0.04, "LIWC": "I"}, {"value": 0.01, "LIWC": "We"}, {"value": 0.0066666667, "LIWC": "They"}, {"value": 0.0633333333, "LIWC": "Social"}, {"value": 0.0, "LIWC": "Family"}, {"value": 0.0033333333, "LIWC": "Friends"}, {"value": 0.0566666667, "LIWC": "Affect"}]}, {"YEAR": "2015", "values": [{"value": 0.026, "LIWC": "I"}, {"value": 0.0, "LIWC": "We"}, {"value": 0.0086666667, "LIWC": "They"}, {"value": 0.062, "LIWC": "Social"}, {"value": 0.0, "LIWC": "Family"}, {"value": 0.0, "LIWC": "Friends"}, {"value": 0.032, "LIWC": "Affect"}]}, {"YEAR": "2016", "values": [{"value": 0.0266, "LIWC": "I"}, {"value": 0.003, "LIWC": "We"}, {"value": 0.0042, "LIWC": "They"}, {"value": 0.0592, "LIWC": "Social"}, {"value": 0.0, "LIWC": "Family"}, {"value": 0.0002, "LIWC": "Friends"}, {"value": 0.0296, "LIWC": "Affect"}]}, {"YEAR": "2017", "values": [{"value": 0.01775, "LIWC": "I"}, {"value": 0.003, "LIWC": "We"}, {"value": 0.0055, "LIWC": "They"}, {"value": 0.06775, "LIWC": "Social"}, {"value": 0.0, "LIWC": "Family"}, {"value": 0.0, "LIWC": "Friends"}, {"value": 0.0265, "LIWC": "Affect"}]}]