[{"YEAR": "2015", "values": [{"value": 0.0, "LIWC": "I"}, {"value": 0.0, "LIWC": "We"}, {"value": 0.0, "LIWC": "They"}, {"value": 0.12, "LIWC": "Social"}, {"value": 0.0, "LIWC": "Family"}, {"value": 0.0, "LIWC": "Friends"}, {"value": 0.06, "LIWC": "Affect"}]}, {"YEAR": "2016", "values": [{"value": 0.0161111111, "LIWC": "I"}, {"value": 0.0011111111, "LIWC": "We"}, {"value": 0.0061111111, "LIWC": "They"}, {"value": 0.0827777778, "LIWC": "Social"}, {"value": 0.0022222222, "LIWC": "Family"}, {"value": 0.0016666667, "LIWC": "Friends"}, {"value": 0.0394444444, "LIWC": "Affect"}]}, {"YEAR": "2017", "values": [{"value": 0.0085714286, "LIWC": "I"}, {"value": 0.0014285714, "LIWC": "We"}, {"value": 0.0057142857, "LIWC": "They"}, {"value": 0.0542857143, "LIWC": "Social"}, {"value": 0.0014285714, "LIWC": "Family"}, {"value": 0.0, "LIWC": "Friends"}, {"value": 0.0357142857, "LIWC": "Affect"}]}]