[{"YEAR": "2014", "values": [{"value": 0.86, "LIWC": "I"}, {"value": 0.03, "LIWC": "We"}, {"value": 0.32, "LIWC": "They"}, {"value": 2.7, "LIWC": "Social"}, {"value": 0.01, "LIWC": "Family"}, {"value": 0.02, "LIWC": "Friends"}, {"value": 1.51, "LIWC": "Affect"}]}, {"YEAR": "2015", "values": [{"value": 0.7, "LIWC": "I"}, {"value": 0.21, "LIWC": "We"}, {"value": 0.43, "LIWC": "They"}, {"value": 2.8, "LIWC": "Social"}, {"value": 0.0, "LIWC": "Family"}, {"value": 0.0, "LIWC": "Friends"}, {"value": 2.12, "LIWC": "Affect"}]}, {"YEAR": "2016", "values": [{"value": 0.61, "LIWC": "I"}, {"value": 0.16, "LIWC": "We"}, {"value": 0.44, "LIWC": "They"}, {"value": 2.34, "LIWC": "Social"}, {"value": 0.0, "LIWC": "Family"}, {"value": 0.0, "LIWC": "Friends"}, {"value": 1.49, "LIWC": "Affect"}]}, {"YEAR": "2017", "values": [{"value": 0.14, "LIWC": "I"}, {"value": 0.05, "LIWC": "We"}, {"value": 0.03, "LIWC": "They"}, {"value": 0.47, "LIWC": "Social"}, {"value": 0.0, "LIWC": "Family"}, {"value": 0.01, "LIWC": "Friends"}, {"value": 0.22, "LIWC": "Affect"}]}]