[{"YEAR": "2014", "values": [{"value": 0.0124444444, "LIWC": "I"}, {"value": 0.004, "LIWC": "We"}, {"value": 0.0068888889, "LIWC": "They"}, {"value": 0.0777777778, "LIWC": "Social"}, {"value": 0.0011111111, "LIWC": "Family"}, {"value": 0.0004444444, "LIWC": "Friends"}, {"value": 0.0491111111, "LIWC": "Affect"}]}, {"YEAR": "2015", "values": [{"value": 0.007037037, "LIWC": "I"}, {"value": 0.002962963, "LIWC": "We"}, {"value": 0.0022222222, "LIWC": "They"}, {"value": 0.0714814815, "LIWC": "Social"}, {"value": 0.0003703704, "LIWC": "Family"}, {"value": 0.0003703704, "LIWC": "Friends"}, {"value": 0.0388888889, "LIWC": "Affect"}]}, {"YEAR": "2016", "values": [{"value": 0.02, "LIWC": "I"}, {"value": 0.0052941176, "LIWC": "We"}, {"value": 0.0047058824, "LIWC": "They"}, {"value": 0.0729411765, "LIWC": "Social"}, {"value": 0.0, "LIWC": "Family"}, {"value": 0.0, "LIWC": "Friends"}, {"value": 0.0429411765, "LIWC": "Affect"}]}, {"YEAR": "2017", "values": [{"value": 0.0175, "LIWC": "I"}, {"value": 0.0075, "LIWC": "We"}, {"value": 0.0025, "LIWC": "They"}, {"value": 0.07, "LIWC": "Social"}, {"value": 0.0, "LIWC": "Family"}, {"value": 0.00125, "LIWC": "Friends"}, {"value": 0.03875, "LIWC": "Affect"}]}]