[{"YEAR": "2014", "values": [{"value": 1.96, "LIWC": "I"}, {"value": 0.16, "LIWC": "We"}, {"value": 0.17, "LIWC": "They"}, {"value": 4.37, "LIWC": "Social"}, {"value": 0.07, "LIWC": "Family"}, {"value": 0.02, "LIWC": "Friends"}, {"value": 2.39, "LIWC": "Affect"}]}, {"YEAR": "2015", "values": [{"value": 1.67, "LIWC": "I"}, {"value": 0.34, "LIWC": "We"}, {"value": 0.18, "LIWC": "They"}, {"value": 4.63, "LIWC": "Social"}, {"value": 0.01, "LIWC": "Family"}, {"value": 0.07, "LIWC": "Friends"}, {"value": 2.05, "LIWC": "Affect"}]}, {"YEAR": "2016", "values": [{"value": 2.01, "LIWC": "I"}, {"value": 0.57, "LIWC": "We"}, {"value": 0.39, "LIWC": "They"}, {"value": 8.12, "LIWC": "Social"}, {"value": 0.13, "LIWC": "Family"}, {"value": 0.07, "LIWC": "Friends"}, {"value": 4.02, "LIWC": "Affect"}]}, {"YEAR": "2017", "values": [{"value": 0.56, "LIWC": "I"}, {"value": 0.25, "LIWC": "We"}, {"value": 0.08, "LIWC": "They"}, {"value": 3.42, "LIWC": "Social"}, {"value": 0.04, "LIWC": "Family"}, {"value": 0.03, "LIWC": "Friends"}, {"value": 1.57, "LIWC": "Affect"}]}]