[{"YEAR": "2014", "values": [{"value": 0.0414285714, "LIWC": "I"}, {"value": 0.0033333333, "LIWC": "We"}, {"value": 0.0052380952, "LIWC": "They"}, {"value": 0.0733333333, "LIWC": "Social"}, {"value": 0.000952381, "LIWC": "Family"}, {"value": 0.0004761905, "LIWC": "Friends"}, {"value": 0.0414285714, "LIWC": "Affect"}]}, {"YEAR": "2015", "values": [{"value": 0.0465517241, "LIWC": "I"}, {"value": 0.0024137931, "LIWC": "We"}, {"value": 0.0062068966, "LIWC": "They"}, {"value": 0.0679310345, "LIWC": "Social"}, {"value": 0.0010344828, "LIWC": "Family"}, {"value": 0.0006896552, "LIWC": "Friends"}, {"value": 0.0382758621, "LIWC": "Affect"}]}, {"YEAR": "2016", "values": [{"value": 0.0286486486, "LIWC": "I"}, {"value": 0.0040540541, "LIWC": "We"}, {"value": 0.0027027027, "LIWC": "They"}, {"value": 0.0710810811, "LIWC": "Social"}, {"value": 0.0005405405, "LIWC": "Family"}, {"value": 0.0018918919, "LIWC": "Friends"}, {"value": 0.0337837838, "LIWC": "Affect"}]}, {"YEAR": "2017", "values": [{"value": 0.0111111111, "LIWC": "I"}, {"value": 0.0072222222, "LIWC": "We"}, {"value": 0.0005555556, "LIWC": "They"}, {"value": 0.0455555556, "LIWC": "Social"}, {"value": 0.0011111111, "LIWC": "Family"}, {"value": 0.0, "LIWC": "Friends"}, {"value": 0.0433333333, "LIWC": "Affect"}]}]