[{"YEAR": "2014", "values": [{"value": 0.0110526316, "LIWC": "I"}, {"value": 0.0052631579, "LIWC": "We"}, {"value": 0.0015789474, "LIWC": "They"}, {"value": 0.0684210526, "LIWC": "Social"}, {"value": 0.0, "LIWC": "Family"}, {"value": 0.0005263158, "LIWC": "Friends"}, {"value": 0.0378947368, "LIWC": "Affect"}]}, {"YEAR": "2015", "values": [{"value": 0.0042857143, "LIWC": "I"}, {"value": 0.0035714286, "LIWC": "We"}, {"value": 0.0035714286, "LIWC": "They"}, {"value": 0.08, "LIWC": "Social"}, {"value": 0.0, "LIWC": "Family"}, {"value": 0.0, "LIWC": "Friends"}, {"value": 0.0314285714, "LIWC": "Affect"}]}, {"YEAR": "2016", "values": [{"value": 0.01, "LIWC": "I"}, {"value": 0.0133333333, "LIWC": "We"}, {"value": 0.0033333333, "LIWC": "They"}, {"value": 0.0733333333, "LIWC": "Social"}, {"value": 0.0, "LIWC": "Family"}, {"value": 0.0, "LIWC": "Friends"}, {"value": 0.03, "LIWC": "Affect"}]}, {"YEAR": "2017", "values": [{"value": 0.0, "LIWC": "I"}, {"value": 0.0, "LIWC": "We"}, {"value": 0.0, "LIWC": "They"}, {"value": 0.03, "LIWC": "Social"}, {"value": 0.0, "LIWC": "Family"}, {"value": 0.0, "LIWC": "Friends"}, {"value": 0.02, "LIWC": "Affect"}]}]