[{"YEAR": "2014", "values": [{"value": 0.0151260504, "LIWC": "Body"}, {"value": 0.0005882353, "LIWC": "Health"}, {"value": 0.0002521008, "LIWC": "Sexual"}, {"value": 0.0004201681, "LIWC": "Relig"}, {"value": 0.0, "LIWC": "Death"}]}, {"YEAR": "2015", "values": [{"value": 0.0146621622, "LIWC": "Body"}, {"value": 0.0006756757, "LIWC": "Health"}, {"value": 0.0001351351, "LIWC": "Sexual"}, {"value": 0.0, "LIWC": "Relig"}, {"value": 0.0001351351, "LIWC": "Death"}]}, {"YEAR": "2016", "values": [{"value": 0.0179710145, "LIWC": "Body"}, {"value": 0.0014492754, "LIWC": "Health"}, {"value": 0.0002173913, "LIWC": "Sexual"}, {"value": 0.0001449275, "LIWC": "Relig"}, {"value": 0.0002173913, "LIWC": "Death"}]}, {"YEAR": "2017", "values": [{"value": 0.0135555556, "LIWC": "Body"}, {"value": 0.0008888889, "LIWC": "Health"}, {"value": 0.0, "LIWC": "Sexual"}, {"value": 0.0013333333, "LIWC": "Relig"}, {"value": 0.0, "LIWC": "Death"}]}]