[{"YEAR": "2015", "values": [{"value": 0.0139393939, "LIWC": "Body"}, {"value": 0.0018181818, "LIWC": "Health"}, {"value": 0.0275757576, "LIWC": "Sexual"}, {"value": 0.0009090909, "LIWC": "Relig"}, {"value": 0.0, "LIWC": "Death"}]}, {"YEAR": "2016", "values": [{"value": 0.01125, "LIWC": "Body"}, {"value": 0.0025, "LIWC": "Health"}, {"value": 0.0209375, "LIWC": "Sexual"}, {"value": 0.0003125, "LIWC": "Relig"}, {"value": 0.0003125, "LIWC": "Death"}]}, {"YEAR": "2017", "values": [{"value": 0.0111111111, "LIWC": "Body"}, {"value": 0.0, "LIWC": "Health"}, {"value": 0.0177777778, "LIWC": "Sexual"}, {"value": 0.0, "LIWC": "Relig"}, {"value": 0.0, "LIWC": "Death"}]}]