[{"YEAR": "2015", "values": [{"value": 0.0142105263, "LIWC": "Body"}, {"value": 0.0005263158, "LIWC": "Health"}, {"value": 0.0, "LIWC": "Sexual"}, {"value": 0.0047368421, "LIWC": "Relig"}, {"value": 0.0068421053, "LIWC": "Death"}]}, {"YEAR": "2016", "values": [{"value": 0.0276923077, "LIWC": "Body"}, {"value": 0.0, "LIWC": "Health"}, {"value": 0.0015384615, "LIWC": "Sexual"}, {"value": 0.0015384615, "LIWC": "Relig"}, {"value": 0.0061538462, "LIWC": "Death"}]}, {"YEAR": "2017", "values": [{"value": 0.018, "LIWC": "Body"}, {"value": 0.004, "LIWC": "Health"}, {"value": 0.0, "LIWC": "Sexual"}, {"value": 0.0, "LIWC": "Relig"}, {"value": 0.002, "LIWC": "Death"}]}]