[{"YEAR": "2014", "values": [{"value": 0.0125263158, "LIWC": "Body"}, {"value": 0.0005263158, "LIWC": "Health"}, {"value": 0.0007368421, "LIWC": "Sexual"}, {"value": 0.0003157895, "LIWC": "Relig"}, {"value": 0.0006315789, "LIWC": "Death"}]}, {"YEAR": "2015", "values": [{"value": 0.0107142857, "LIWC": "Body"}, {"value": 0.0001785714, "LIWC": "Health"}, {"value": 0.0003571429, "LIWC": "Sexual"}, {"value": 0.0003571429, "LIWC": "Relig"}, {"value": 0.0001785714, "LIWC": "Death"}]}, {"YEAR": "2016", "values": [{"value": 0.0106024096, "LIWC": "Body"}, {"value": 0.0003614458, "LIWC": "Health"}, {"value": 0.0002409639, "LIWC": "Sexual"}, {"value": 0.0002409639, "LIWC": "Relig"}, {"value": 0.0007228916, "LIWC": "Death"}]}, {"YEAR": "2017", "values": [{"value": 0.0115, "LIWC": "Body"}, {"value": 0.0, "LIWC": "Health"}, {"value": 0.0, "LIWC": "Sexual"}, {"value": 0.0015, "LIWC": "Relig"}, {"value": 0.0, "LIWC": "Death"}]}]