[{"YEAR": "2014", "values": [{"value": 0.0561290323, "LIWC": "Work"}, {"value": 0.0101612903, "LIWC": "Achiev"}, {"value": 0.0169354839, "LIWC": "Leisure"}, {"value": 0.0016129032, "LIWC": "Home"}, {"value": 0.005, "LIWC": "Money"}]}, {"YEAR": "2015", "values": [{"value": 0.0491428571, "LIWC": "Work"}, {"value": 0.0074285714, "LIWC": "Achiev"}, {"value": 0.0064285714, "LIWC": "Leisure"}, {"value": 0.0021428571, "LIWC": "Home"}, {"value": 0.0078571429, "LIWC": "Money"}]}, {"YEAR": "2016", "values": [{"value": 0.0486792453, "LIWC": "Work"}, {"value": 0.0062264151, "LIWC": "Achiev"}, {"value": 0.0128301887, "LIWC": "Leisure"}, {"value": 0.000754717, "LIWC": "Home"}, {"value": 0.0049056604, "LIWC": "Money"}]}, {"YEAR": "2017", "values": [{"value": 0.0532142857, "LIWC": "Work"}, {"value": 0.0089285714, "LIWC": "Achiev"}, {"value": 0.0110714286, "LIWC": "Leisure"}, {"value": 0.0010714286, "LIWC": "Home"}, {"value": 0.0042857143, "LIWC": "Money"}]}]