[{"YEAR": "2014", "values": [{"value": 0.0346153846, "LIWC": "Work"}, {"value": 0.0138461538, "LIWC": "Achiev"}, {"value": 0.0030769231, "LIWC": "Leisure"}, {"value": 0.0007692308, "LIWC": "Home"}, {"value": 0.0030769231, "LIWC": "Money"}]}, {"YEAR": "2015", "values": [{"value": 0.0333333333, "LIWC": "Work"}, {"value": 0.0066666667, "LIWC": "Achiev"}, {"value": 0.0008333333, "LIWC": "Leisure"}, {"value": 0.0, "LIWC": "Home"}, {"value": 0.0033333333, "LIWC": "Money"}]}, {"YEAR": "2016", "values": [{"value": 0.0305263158, "LIWC": "Work"}, {"value": 0.0194736842, "LIWC": "Achiev"}, {"value": 0.0015789474, "LIWC": "Leisure"}, {"value": 0.0, "LIWC": "Home"}, {"value": 0.0015789474, "LIWC": "Money"}]}, {"YEAR": "2017", "values": [{"value": 0.0342857143, "LIWC": "Work"}, {"value": 0.0171428571, "LIWC": "Achiev"}, {"value": 0.0057142857, "LIWC": "Leisure"}, {"value": 0.0, "LIWC": "Home"}, {"value": 0.0142857143, "LIWC": "Money"}]}]