[{"YEAR": "2014", "values": [{"value": 0.0288888889, "LIWC": "Work"}, {"value": 0.0116666667, "LIWC": "Achiev"}, {"value": 0.0038888889, "LIWC": "Leisure"}, {"value": 0.0016666667, "LIWC": "Home"}, {"value": 0.0005555556, "LIWC": "Money"}]}, {"YEAR": "2015", "values": [{"value": 0.024047619, "LIWC": "Work"}, {"value": 0.0104761905, "LIWC": "Achiev"}, {"value": 0.0078571429, "LIWC": "Leisure"}, {"value": 0.000952381, "LIWC": "Home"}, {"value": 0.0016666667, "LIWC": "Money"}]}, {"YEAR": "2016", "values": [{"value": 0.0417857143, "LIWC": "Work"}, {"value": 0.0114285714, "LIWC": "Achiev"}, {"value": 0.0042857143, "LIWC": "Leisure"}, {"value": 0.0011904762, "LIWC": "Home"}, {"value": 0.0032142857, "LIWC": "Money"}]}, {"YEAR": "2017", "values": [{"value": 0.0358333333, "LIWC": "Work"}, {"value": 0.0075, "LIWC": "Achiev"}, {"value": 0.0058333333, "LIWC": "Leisure"}, {"value": 0.0008333333, "LIWC": "Home"}, {"value": 0.0033333333, "LIWC": "Money"}]}]