[{"YEAR": "2014", "values": [{"value": 0.4, "LIWC": "Work"}, {"value": 0.29, "LIWC": "Achiev"}, {"value": 0.13, "LIWC": "Leisure"}, {"value": 0.07, "LIWC": "Home"}, {"value": 0.06, "LIWC": "Money"}]}, {"YEAR": "2015", "values": [{"value": 1.13, "LIWC": "Work"}, {"value": 0.34, "LIWC": "Achiev"}, {"value": 0.18, "LIWC": "Leisure"}, {"value": 0.07, "LIWC": "Home"}, {"value": 0.14, "LIWC": "Money"}]}, {"YEAR": "2016", "values": [{"value": 3.55, "LIWC": "Work"}, {"value": 0.83, "LIWC": "Achiev"}, {"value": 0.47, "LIWC": "Leisure"}, {"value": 0.1, "LIWC": "Home"}, {"value": 0.27, "LIWC": "Money"}]}, {"YEAR": "2017", "values": [{"value": 1.49, "LIWC": "Work"}, {"value": 0.34, "LIWC": "Achiev"}, {"value": 0.05, "LIWC": "Leisure"}, {"value": 0.01, "LIWC": "Home"}, {"value": 0.02, "LIWC": "Money"}]}]