[{"YEAR": "2014", "values": [{"value": 0.0548, "LIWC": "Work"}, {"value": 0.0128, "LIWC": "Achiev"}, {"value": 0.0064, "LIWC": "Leisure"}, {"value": 0.0, "LIWC": "Home"}, {"value": 0.0104, "LIWC": "Money"}]}, {"YEAR": "2015", "values": [{"value": 0.0456603774, "LIWC": "Work"}, {"value": 0.0167924528, "LIWC": "Achiev"}, {"value": 0.0152830189, "LIWC": "Leisure"}, {"value": 0.0001886792, "LIWC": "Home"}, {"value": 0.0149056604, "LIWC": "Money"}]}, {"YEAR": "2016", "values": [{"value": 0.0507692308, "LIWC": "Work"}, {"value": 0.0115384615, "LIWC": "Achiev"}, {"value": 0.0038461538, "LIWC": "Leisure"}, {"value": 0.0, "LIWC": "Home"}, {"value": 0.0161538462, "LIWC": "Money"}]}]