[{"YEAR": "2014", "values": [{"value": 0.0406666667, "LIWC": "Work"}, {"value": 0.026, "LIWC": "Achiev"}, {"value": 0.016, "LIWC": "Leisure"}, {"value": 0.004, "LIWC": "Home"}, {"value": 0.0113333333, "LIWC": "Money"}]}, {"YEAR": "2015", "values": [{"value": 0.0495652174, "LIWC": "Work"}, {"value": 0.0226086957, "LIWC": "Achiev"}, {"value": 0.0082608696, "LIWC": "Leisure"}, {"value": 0.0043478261, "LIWC": "Home"}, {"value": 0.0034782609, "LIWC": "Money"}]}, {"YEAR": "2016", "values": [{"value": 0.0413636364, "LIWC": "Work"}, {"value": 0.025, "LIWC": "Achiev"}, {"value": 0.0059090909, "LIWC": "Leisure"}, {"value": 0.0009090909, "LIWC": "Home"}, {"value": 0.0054545455, "LIWC": "Money"}]}, {"YEAR": "2017", "values": [{"value": 0.032, "LIWC": "Work"}, {"value": 0.022, "LIWC": "Achiev"}, {"value": 0.012, "LIWC": "Leisure"}, {"value": 0.004, "LIWC": "Home"}, {"value": 0.01, "LIWC": "Money"}]}]