[{"YEAR": "2014", "values": [{"value": 0.0314285714, "LIWC": "Work"}, {"value": 0.0142857143, "LIWC": "Achiev"}, {"value": 0.0028571429, "LIWC": "Leisure"}, {"value": 0.0028571429, "LIWC": "Home"}, {"value": 0.0014285714, "LIWC": "Money"}]}, {"YEAR": "2015", "values": [{"value": 0.0245, "LIWC": "Work"}, {"value": 0.0105, "LIWC": "Achiev"}, {"value": 0.007, "LIWC": "Leisure"}, {"value": 0.001, "LIWC": "Home"}, {"value": 0.006, "LIWC": "Money"}]}, {"YEAR": "2016", "values": [{"value": 0.0212121212, "LIWC": "Work"}, {"value": 0.0124242424, "LIWC": "Achiev"}, {"value": 0.0096969697, "LIWC": "Leisure"}, {"value": 0.0006060606, "LIWC": "Home"}, {"value": 0.0021212121, "LIWC": "Money"}]}, {"YEAR": "2017", "values": [{"value": 0.0335294118, "LIWC": "Work"}, {"value": 0.0135294118, "LIWC": "Achiev"}, {"value": 0.0076470588, "LIWC": "Leisure"}, {"value": 0.0029411765, "LIWC": "Home"}, {"value": 0.0023529412, "LIWC": "Money"}]}]