[{"YEAR": "2014", "values": [{"value": 0.0377777778, "LIWC": "Work"}, {"value": 0.0348888889, "LIWC": "Achiev"}, {"value": 0.0171111111, "LIWC": "Leisure"}, {"value": 0.0002222222, "LIWC": "Home"}, {"value": 0.0075555556, "LIWC": "Money"}]}, {"YEAR": "2015", "values": [{"value": 0.0351851852, "LIWC": "Work"}, {"value": 0.0137037037, "LIWC": "Achiev"}, {"value": 0.0025925926, "LIWC": "Leisure"}, {"value": 0.0003703704, "LIWC": "Home"}, {"value": 0.0011111111, "LIWC": "Money"}]}, {"YEAR": "2016", "values": [{"value": 0.0223529412, "LIWC": "Work"}, {"value": 0.0105882353, "LIWC": "Achiev"}, {"value": 0.0070588235, "LIWC": "Leisure"}, {"value": 0.0011764706, "LIWC": "Home"}, {"value": 0.0064705882, "LIWC": "Money"}]}, {"YEAR": "2017", "values": [{"value": 0.03, "LIWC": "Work"}, {"value": 0.005, "LIWC": "Achiev"}, {"value": 0.00375, "LIWC": "Leisure"}, {"value": 0.0, "LIWC": "Home"}, {"value": 0.00125, "LIWC": "Money"}]}]