[{"YEAR": "2014", "values": [{"value": 0.02, "LIWC": "Work"}, {"value": 0.015, "LIWC": "Achiev"}, {"value": 0.0, "LIWC": "Leisure"}, {"value": 0.0, "LIWC": "Home"}, {"value": 0.005, "LIWC": "Money"}]}, {"YEAR": "2015", "values": [{"value": 0.0388235294, "LIWC": "Work"}, {"value": 0.0147058824, "LIWC": "Achiev"}, {"value": 0.0052941176, "LIWC": "Leisure"}, {"value": 0.0, "LIWC": "Home"}, {"value": 0.0082352941, "LIWC": "Money"}]}, {"YEAR": "2016", "values": [{"value": 0.0361538462, "LIWC": "Work"}, {"value": 0.0184615385, "LIWC": "Achiev"}, {"value": 0.005, "LIWC": "Leisure"}, {"value": 0.0, "LIWC": "Home"}, {"value": 0.0088461538, "LIWC": "Money"}]}, {"YEAR": "2017", "values": [{"value": 0.045, "LIWC": "Work"}, {"value": 0.015, "LIWC": "Achiev"}, {"value": 0.0075, "LIWC": "Leisure"}, {"value": 0.0, "LIWC": "Home"}, {"value": 0.0075, "LIWC": "Money"}]}]