[{"YEAR": "2014", "values": [{"value": 0.0633333333, "LIWC": "Work"}, {"value": 0.0033333333, "LIWC": "Achiev"}, {"value": 0.0066666667, "LIWC": "Leisure"}, {"value": 0.0, "LIWC": "Home"}, {"value": 0.0, "LIWC": "Money"}]}, {"YEAR": "2015", "values": [{"value": 0.0286666667, "LIWC": "Work"}, {"value": 0.0266666667, "LIWC": "Achiev"}, {"value": 0.02, "LIWC": "Leisure"}, {"value": 0.0013333333, "LIWC": "Home"}, {"value": 0.0053333333, "LIWC": "Money"}]}, {"YEAR": "2016", "values": [{"value": 0.0410502283, "LIWC": "Work"}, {"value": 0.0176255708, "LIWC": "Achiev"}, {"value": 0.0165753425, "LIWC": "Leisure"}, {"value": 0.0001826484, "LIWC": "Home"}, {"value": 0.0042465753, "LIWC": "Money"}]}, {"YEAR": "2017", "values": [{"value": 0.0378947368, "LIWC": "Work"}, {"value": 0.0248421053, "LIWC": "Achiev"}, {"value": 0.0205263158, "LIWC": "Leisure"}, {"value": 0.0008421053, "LIWC": "Home"}, {"value": 0.0045263158, "LIWC": "Money"}]}]