[{"YEAR": "2014", "values": [{"value": 0.0357894737, "LIWC": "Work"}, {"value": 0.0115789474, "LIWC": "Achiev"}, {"value": 0.0094736842, "LIWC": "Leisure"}, {"value": 0.0031578947, "LIWC": "Home"}, {"value": 0.0121052632, "LIWC": "Money"}]}, {"YEAR": "2015", "values": [{"value": 0.032173913, "LIWC": "Work"}, {"value": 0.012173913, "LIWC": "Achiev"}, {"value": 0.0186956522, "LIWC": "Leisure"}, {"value": 0.0073913043, "LIWC": "Home"}, {"value": 0.0156521739, "LIWC": "Money"}]}, {"YEAR": "2016", "values": [{"value": 0.03375, "LIWC": "Work"}, {"value": 0.0175, "LIWC": "Achiev"}, {"value": 0.01125, "LIWC": "Leisure"}, {"value": 0.01125, "LIWC": "Home"}, {"value": 0.01125, "LIWC": "Money"}]}]