[{"YEAR": "2014", "values": [{"value": 0.0647619048, "LIWC": "Work"}, {"value": 0.0223809524, "LIWC": "Achiev"}, {"value": 0.0042857143, "LIWC": "Leisure"}, {"value": 0.0, "LIWC": "Home"}, {"value": 0.0, "LIWC": "Money"}]}, {"YEAR": "2015", "values": [{"value": 0.0704166667, "LIWC": "Work"}, {"value": 0.0170833333, "LIWC": "Achiev"}, {"value": 0.0045833333, "LIWC": "Leisure"}, {"value": 0.0, "LIWC": "Home"}, {"value": 0.0008333333, "LIWC": "Money"}]}, {"YEAR": "2016", "values": [{"value": 0.06125, "LIWC": "Work"}, {"value": 0.023125, "LIWC": "Achiev"}, {"value": 0.0, "LIWC": "Leisure"}, {"value": 0.0, "LIWC": "Home"}, {"value": 0.0, "LIWC": "Money"}]}, {"YEAR": "2017", "values": [{"value": 0.0666666667, "LIWC": "Work"}, {"value": 0.0183333333, "LIWC": "Achiev"}, {"value": 0.0066666667, "LIWC": "Leisure"}, {"value": 0.0, "LIWC": "Home"}, {"value": 0.0, "LIWC": "Money"}]}]