[{"YEAR": "2014", "values": [{"value": 0.04, "LIWC": "Posemo"}, {"value": 0.0060344828, "LIWC": "Negemo"}, {"value": 0.0010344828, "LIWC": "Anx"}, {"value": 0.0006896552, "LIWC": "Anger"}, {"value": 0.0010344828, "LIWC": "Sad"}]}, {"YEAR": "2015", "values": [{"value": 0.0367391304, "LIWC": "Posemo"}, {"value": 0.0052173913, "LIWC": "Negemo"}, {"value": 0.0008695652, "LIWC": "Anx"}, {"value": 0.0008695652, "LIWC": "Anger"}, {"value": 0.0002173913, "LIWC": "Sad"}]}, {"YEAR": "2016", "values": [{"value": 0.0386567164, "LIWC": "Posemo"}, {"value": 0.0076119403, "LIWC": "Negemo"}, {"value": 0.0008955224, "LIWC": "Anx"}, {"value": 0.0010447761, "LIWC": "Anger"}, {"value": 0.0017910448, "LIWC": "Sad"}]}, {"YEAR": "2017", "values": [{"value": 0.035, "LIWC": "Posemo"}, {"value": 0.0070833333, "LIWC": "Negemo"}, {"value": 0.0016666667, "LIWC": "Anx"}, {"value": 0.00125, "LIWC": "Anger"}, {"value": 0.0016666667, "LIWC": "Sad"}]}]