[{"YEAR": "2014", "values": [{"value": 0.0436, "LIWC": "Posemo"}, {"value": 0.0216, "LIWC": "Negemo"}, {"value": 0.0048, "LIWC": "Anx"}, {"value": 0.008, "LIWC": "Anger"}, {"value": 0.0032, "LIWC": "Sad"}]}, {"YEAR": "2015", "values": [{"value": 0.0353333333, "LIWC": "Posemo"}, {"value": 0.0171111111, "LIWC": "Negemo"}, {"value": 0.0028888889, "LIWC": "Anx"}, {"value": 0.0062222222, "LIWC": "Anger"}, {"value": 0.0035555556, "LIWC": "Sad"}]}, {"YEAR": "2016", "values": [{"value": 0.0231632653, "LIWC": "Posemo"}, {"value": 0.0162244898, "LIWC": "Negemo"}, {"value": 0.0033673469, "LIWC": "Anx"}, {"value": 0.0067346939, "LIWC": "Anger"}, {"value": 0.0026530612, "LIWC": "Sad"}]}, {"YEAR": "2017", "values": [{"value": 0.0308571429, "LIWC": "Posemo"}, {"value": 0.0097142857, "LIWC": "Negemo"}, {"value": 0.0005714286, "LIWC": "Anx"}, {"value": 0.0054285714, "LIWC": "Anger"}, {"value": 0.0011428571, "LIWC": "Sad"}]}]