[{"YEAR": "2014", "values": [{"value": 0.0246376812, "LIWC": "Posemo"}, {"value": 0.015942029, "LIWC": "Negemo"}, {"value": 0.0005797101, "LIWC": "Anx"}, {"value": 0.0060869565, "LIWC": "Anger"}, {"value": 0.0014492754, "LIWC": "Sad"}]}, {"YEAR": "2015", "values": [{"value": 0.0267901235, "LIWC": "Posemo"}, {"value": 0.0155555556, "LIWC": "Negemo"}, {"value": 0.0014814815, "LIWC": "Anx"}, {"value": 0.0064197531, "LIWC": "Anger"}, {"value": 0.0022222222, "LIWC": "Sad"}]}, {"YEAR": "2016", "values": [{"value": 0.026, "LIWC": "Posemo"}, {"value": 0.0191428571, "LIWC": "Negemo"}, {"value": 0.0021428571, "LIWC": "Anx"}, {"value": 0.0075714286, "LIWC": "Anger"}, {"value": 0.0027142857, "LIWC": "Sad"}]}, {"YEAR": "2017", "values": [{"value": 0.0326666667, "LIWC": "Posemo"}, {"value": 0.014, "LIWC": "Negemo"}, {"value": 0.0, "LIWC": "Anx"}, {"value": 0.0066666667, "LIWC": "Anger"}, {"value": 0.0006666667, "LIWC": "Sad"}]}]