[{"YEAR": "2015", "values": [{"value": 2.57, "LIWC": "Posemo"}, {"value": 1.42, "LIWC": "Negemo"}, {"value": 0.12, "LIWC": "Anx"}, {"value": 0.65, "LIWC": "Anger"}, {"value": 0.23, "LIWC": "Sad"}]}, {"YEAR": "2016", "values": [{"value": 3.0, "LIWC": "Posemo"}, {"value": 1.72, "LIWC": "Negemo"}, {"value": 0.1, "LIWC": "Anx"}, {"value": 0.87, "LIWC": "Anger"}, {"value": 0.23, "LIWC": "Sad"}]}, {"YEAR": "2017", "values": [{"value": 0.56, "LIWC": "Posemo"}, {"value": 0.28, "LIWC": "Negemo"}, {"value": 0.0, "LIWC": "Anx"}, {"value": 0.15, "LIWC": "Anger"}, {"value": 0.0, "LIWC": "Sad"}]}]