[{"YEAR": "2014", "values": [{"value": 19.75, "LIWC": "Posemo"}, {"value": 5.49, "LIWC": "Negemo"}, {"value": 0.68, "LIWC": "Anx"}, {"value": 2.15, "LIWC": "Anger"}, {"value": 0.63, "LIWC": "Sad"}]}, {"YEAR": "2015", "values": [{"value": 5.36, "LIWC": "Posemo"}, {"value": 1.7, "LIWC": "Negemo"}, {"value": 0.19, "LIWC": "Anx"}, {"value": 0.79, "LIWC": "Anger"}, {"value": 0.12, "LIWC": "Sad"}]}, {"YEAR": "2016", "values": [{"value": 2.32, "LIWC": "Posemo"}, {"value": 1.06, "LIWC": "Negemo"}, {"value": 0.15, "LIWC": "Anx"}, {"value": 0.48, "LIWC": "Anger"}, {"value": 0.09, "LIWC": "Sad"}]}, {"YEAR": "2017", "values": [{"value": 1.09, "LIWC": "Posemo"}, {"value": 0.44, "LIWC": "Negemo"}, {"value": 0.25, "LIWC": "Anx"}, {"value": 0.03, "LIWC": "Anger"}, {"value": 0.06, "LIWC": "Sad"}]}]