[{"YEAR": "2015", "values": [{"value": 0.0, "LIWC": "Posemo"}, {"value": 0.0, "LIWC": "Negemo"}, {"value": 0.0, "LIWC": "Anx"}, {"value": 0.0, "LIWC": "Anger"}, {"value": 0.0, "LIWC": "Sad"}]}, {"YEAR": "2016", "values": [{"value": 0.0133333333, "LIWC": "Posemo"}, {"value": 0.0246666667, "LIWC": "Negemo"}, {"value": 0.004, "LIWC": "Anx"}, {"value": 0.0, "LIWC": "Anger"}, {"value": 0.01, "LIWC": "Sad"}]}, {"YEAR": "2017", "values": [{"value": 0.0171428571, "LIWC": "Posemo"}, {"value": 0.0257142857, "LIWC": "Negemo"}, {"value": 0.0014285714, "LIWC": "Anx"}, {"value": 0.0014285714, "LIWC": "Anger"}, {"value": 0.0142857143, "LIWC": "Sad"}]}]