[{"YEAR": "2014", "values": [{"value": 0.025, "LIWC": "Posemo"}, {"value": 0.0096666667, "LIWC": "Negemo"}, {"value": 0.0013333333, "LIWC": "Anx"}, {"value": 0.0043333333, "LIWC": "Anger"}, {"value": 0.0006666667, "LIWC": "Sad"}]}, {"YEAR": "2015", "values": [{"value": 0.0173076923, "LIWC": "Posemo"}, {"value": 0.0119230769, "LIWC": "Negemo"}, {"value": 0.0019230769, "LIWC": "Anx"}, {"value": 0.0042307692, "LIWC": "Anger"}, {"value": 0.0007692308, "LIWC": "Sad"}]}, {"YEAR": "2016", "values": [{"value": 0.008, "LIWC": "Posemo"}, {"value": 0.014, "LIWC": "Negemo"}, {"value": 0.0, "LIWC": "Anx"}, {"value": 0.008, "LIWC": "Anger"}, {"value": 0.0, "LIWC": "Sad"}]}]