[{"YEAR": "2014", "values": [{"value": 2.35, "LIWC": "Posemo"}, {"value": 1.18, "LIWC": "Negemo"}, {"value": 0.28, "LIWC": "Anx"}, {"value": 0.27, "LIWC": "Anger"}, {"value": 0.19, "LIWC": "Sad"}]}, {"YEAR": "2015", "values": [{"value": 1.87, "LIWC": "Posemo"}, {"value": 0.88, "LIWC": "Negemo"}, {"value": 0.21, "LIWC": "Anx"}, {"value": 0.23, "LIWC": "Anger"}, {"value": 0.11, "LIWC": "Sad"}]}, {"YEAR": "2016", "values": [{"value": 1.4, "LIWC": "Posemo"}, {"value": 0.88, "LIWC": "Negemo"}, {"value": 0.25, "LIWC": "Anx"}, {"value": 0.16, "LIWC": "Anger"}, {"value": 0.12, "LIWC": "Sad"}]}, {"YEAR": "2017", "values": [{"value": 0.48, "LIWC": "Posemo"}, {"value": 0.18, "LIWC": "Negemo"}, {"value": 0.05, "LIWC": "Anx"}, {"value": 0.04, "LIWC": "Anger"}, {"value": 0.05, "LIWC": "Sad"}]}]